pytest_external_blockers/__init__.py
pytest_external_blockers-0.1.1.dist-info/LICENSE
pytest_external_blockers-0.1.1.dist-info/METADATA
pytest_external_blockers-0.1.1.dist-info/WHEEL
pytest_external_blockers-0.1.1.dist-info/entry_points.txt
pytest_external_blockers-0.1.1.dist-info/top_level.txt
pytest_external_blockers-0.1.1.dist-info/RECORD
