Metadata-Version: 2.1
Name: pytest-external-blockers
Version: 0.1.1
Summary: a special outcome for tests that are blocked for external reasons
Home-page: https://github.com/RonnyPfannschmidt-RedHat/pytest-external-blockers
License: MIT
Platform: UNKNOWN
Classifier: License :: OSI Approved :: MIT License
License-File: LICENSE
Requires-Dist: attrs
Requires-Dist: pytest
